[
  {
    "model": "ride.ride",
    "pk": 1,
    "fields": {
      "status": "completed",
      "id_rider": 6,
      "id_driver": 5,
      "pickup_latitude": 37.696871,
      "pickup_longitude": -122.495102,
      "dropoff_latitude": 37.609125,
      "dropoff_longitude": -122.150867,
      "pickup_time": "2025-05-05T21:52:45.482001+00:00"
    }
  },
  {
    "model": "ride.ride",
    "pk": 2,
    "fields": {
      "status": "completed",
      "id_rider": 1,
      "id_driver": 6,
      "pickup_latitude": 37.815899,
      "pickup_longitude": -122.387958,
      "dropoff_latitude": 37.713193,
      "dropoff_longitude": -122.184086,
      "pickup_time": "2025-04-25T00:07:08.137416+00:00"
    }
  },
  {
    "model": "ride.ride",
    "pk": 3,
    "fields": {
      "status": "completed",
      "id_rider": 5,
      "id_driver": 3,
      "pickup_latitude": 37.623066,
      "pickup_longitude": -122.493648,
      "dropoff_latitude": 37.639838,
      "dropoff_longitude": -122.187423,
      "pickup_time": "2025-05-08T12:43:15.948764+00:00"
    }
  },
  {
    "model": "ride.ride",
    "pk": 4,
    "fields": {
      "status": "completed",
      "id_rider": 9,
      "id_driver": 10,
      "pickup_latitude": 37.60161,
      "pickup_longitude": -122.148702,
      "dropoff_latitude": 37.677595,
      "dropoff_longitude": -122.311729,
      "pickup_time": "2025-05-21T21:38:14.018910+00:00"
    }
  },
  {
    "model": "ride.ride",
    "pk": 5,
    "fields": {
      "status": "completed",
      "id_rider": 10,
      "id_driver": 1,
      "pickup_latitude": 37.891938,
      "pickup_longitude": -122.270907,
      "dropoff_latitude": 37.888082,
      "dropoff_longitude": -122.2586,
      "pickup_time": "2025-05-12T08:35:55.770111+00:00"
    }
  },
  {
    "model": "ride.ride",
    "pk": 6,
    "fields": {
      "status": "pickup",
      "id_rider": 11,
      "id_driver": 13,
      "pickup_latitude": 37.811948,
      "pickup_longitude": -122.302932,
      "dropoff_latitude": 37.685072,
      "dropoff_longitude": -122.21364,
      "pickup_time": "2025-05-20T01:51:10.666655+00:00"
    }
  },
  {
    "model": "ride.ride",
    "pk": 7,
    "fields": {
      "status": "in-progress",
      "id_rider": 8,
      "id_driver": 1,
      "pickup_latitude": 37.658652,
      "pickup_longitude": -122.481487,
      "dropoff_latitude": 37.639379,
      "dropoff_longitude": -122.428949,
      "pickup_time": "2025-05-16T07:43:33.989983+00:00"
    }
  },
  {
    "model": "ride.ride",
    "pk": 8,
    "fields": {
      "status": "requested",
      "id_rider": 7,
      "id_driver": 5,
      "pickup_latitude": 37.604257,
      "pickup_longitude": -122.375297,
      "dropoff_latitude": 37.835074,
      "dropoff_longitude": -122.191272,
      "pickup_time": "2025-05-06T20:54:35.240744+00:00"
    }
  },
  {
    "model": "ride.ride",
    "pk": 9,
    "fields": {
      "status": "pickup",
      "id_rider": 3,
      "id_driver": 11,
      "pickup_latitude": 37.725303,
      "pickup_longitude": -122.159136,
      "dropoff_latitude": 37.813517,
      "dropoff_longitude": -122.498567,
      "pickup_time": "2025-05-11T20:49:14.932315+00:00"
    }
  },
  {
    "model": "ride.ride",
    "pk": 10,
    "fields": {
      "status": "requested",
      "id_rider": 12,
      "id_driver": 4,
      "pickup_latitude": 37.697516,
      "pickup_longitude": -122.397591,
      "dropoff_latitude": 37.665062,
      "dropoff_longitude": -122.17257,
      "pickup_time": "2025-05-22T11:39:13.664943+00:00"
    }
  },
  {
    "model": "ride.ride",
    "pk": 11,
    "fields": {
      "status": "in-progress",
      "id_rider": 4,
      "id_driver": 3,
      "pickup_latitude": 37.767637,
      "pickup_longitude": -122.1641,
      "dropoff_latitude": 37.667316,
      "dropoff_longitude": -122.101606,
      "pickup_time": "2025-05-09T16:42:46.305537+00:00"
    }
  },
  {
    "model": "ride.ride",
    "pk": 12,
    "fields": {
      "status": "assigned",
      "id_rider": 12,
      "id_driver": 6,
      "pickup_latitude": 37.701036,
      "pickup_longitude": -122.214252,
      "dropoff_latitude": 37.82819,
      "dropoff_longitude": -122.226183,
      "pickup_time": "2025-04-23T00:50:46.910485+00:00"
    }
  },
  {
    "model": "ride.ride",
    "pk": 13,
    "fields": {
      "status": "cancelled",
      "id_rider": 12,
      "id_driver": 6,
      "pickup_latitude": 37.787879,
      "pickup_longitude": -122.234928,
      "dropoff_latitude": 37.65911,
      "dropoff_longitude": -122.104002,
      "pickup_time": "2025-05-08T12:52:23.549146+00:00"
    }
  },
  {
    "model": "ride.ride",
    "pk": 14,
    "fields": {
      "status": "pickup",
      "id_rider": 4,
      "id_driver": 11,
      "pickup_latitude": 37.680077,
      "pickup_longitude": -122.346526,
      "dropoff_latitude": 37.738517,
      "dropoff_longitude": -122.397858,
      "pickup_time": "2025-04-30T11:21:06.202939+00:00"
    }
  },
  {
    "model": "ride.ride",
    "pk": 15,
    "fields": {
      "status": "cancelled",
      "id_rider": 8,
      "id_driver": 5,
      "pickup_latitude": 37.711557,
      "pickup_longitude": -122.3998,
      "dropoff_latitude": 37.827492,
      "dropoff_longitude": -122.246721,
      "pickup_time": "2025-04-25T22:58:42.835922+00:00"
    }
  },
  {
    "model": "ride.ride",
    "pk": 16,
    "fields": {
      "status": "en-route",
      "id_rider": 5,
      "id_driver": 3,
      "pickup_latitude": 37.606103,
      "pickup_longitude": -122.187004,
      "dropoff_latitude": 37.863005,
      "dropoff_longitude": -122.135443,
      "pickup_time": "2025-05-06T17:27:14.270268+00:00"
    }
  },
  {
    "model": "ride.ride",
    "pk": 17,
    "fields": {
      "status": "failed",
      "id_rider": 11,
      "id_driver": 4,
      "pickup_latitude": 37.786335,
      "pickup_longitude": -122.208925,
      "dropoff_latitude": 37.6712,
      "dropoff_longitude": -122.400483,
      "pickup_time": "2025-04-28T20:42:58.040827+00:00"
    }
  },
  {
    "model": "ride.ride",
    "pk": 18,
    "fields": {
      "status": "cancelled",
      "id_rider": 8,
      "id_driver": 10,
      "pickup_latitude": 37.766289,
      "pickup_longitude": -122.364842,
      "dropoff_latitude": 37.701786,
      "dropoff_longitude": -122.464192,
      "pickup_time": "2025-04-29T03:54:33.009848+00:00"
    }
  },
  {
    "model": "ride.ride",
    "pk": 19,
    "fields": {
      "status": "cancelled",
      "id_rider": 1,
      "id_driver": 12,
      "pickup_latitude": 37.822227,
      "pickup_longitude": -122.30768,
      "dropoff_latitude": 37.857118,
      "dropoff_longitude": -122.351173,
      "pickup_time": "2025-04-30T06:18:55.974087+00:00"
    }
  },
  {
    "model": "ride.ride",
    "pk": 20,
    "fields": {
      "status": "failed",
      "id_rider": 2,
      "id_driver": 3,
      "pickup_latitude": 37.609977,
      "pickup_longitude": -122.48861,
      "dropoff_latitude": 37.651735,
      "dropoff_longitude": -122.396291,
      "pickup_time": "2025-04-28T16:53:21.186575+00:00"
    }
  },
  {
    "model": "ride.ride",
    "pk": 21,
    "fields": {
      "status": "in-progress",
      "id_rider": 12,
      "id_driver": 10,
      "pickup_latitude": 37.733676,
      "pickup_longitude": -122.239873,
      "dropoff_latitude": 37.642699,
      "dropoff_longitude": -122.311956,
      "pickup_time": "2025-05-17T10:56:47.411078+00:00"
    }
  },
  {
    "model": "ride.ride",
    "pk": 22,
    "fields": {
      "status": "requested",
      "id_rider": 12,
      "id_driver": 8,
      "pickup_latitude": 37.646588,
      "pickup_longitude": -122.499876,
      "dropoff_latitude": 37.884955,
      "dropoff_longitude": -122.363015,
      "pickup_time": "2025-05-20T05:06:32.075384+00:00"
    }
  },
  {
    "model": "ride.ride",
    "pk": 23,
    "fields": {
      "status": "en-route",
      "id_rider": 11,
      "id_driver": 4,
      "pickup_latitude": 37.637455,
      "pickup_longitude": -122.423865,
      "dropoff_latitude": 37.778383,
      "dropoff_longitude": -122.126988,
      "pickup_time": "2025-04-24T15:15:24.215619+00:00"
    }
  },
  {
    "model": "ride.ride",
    "pk": 24,
    "fields": {
      "status": "failed",
      "id_rider": 10,
      "id_driver": 11,
      "pickup_latitude": 37.813816,
      "pickup_longitude": -122.115059,
      "dropoff_latitude": 37.833815,
      "dropoff_longitude": -122.3221,
      "pickup_time": "2025-05-06T20:20:28.338256+00:00"
    }
  },
  {
    "model": "ride.ride",
    "pk": 25,
    "fields": {
      "status": "assigned",
      "id_rider": 1,
      "id_driver": 7,
      "pickup_latitude": 37.881378,
      "pickup_longitude": -122.122045,
      "dropoff_latitude": 37.616803,
      "dropoff_longitude": -122.4664,
      "pickup_time": "2025-05-02T12:41:36.653993+00:00"
    }
  },
  {
    "model": "ride.ride",
    "pk": 26,
    "fields": {
      "status": "assigned",
      "id_rider": 9,
      "id_driver": 11,
      "pickup_latitude": 37.629486,
      "pickup_longitude": -122.176158,
      "dropoff_latitude": 37.693988,
      "dropoff_longitude": -122.463763,
      "pickup_time": "2025-04-29T21:08:53.481763+00:00"
    }
  },
  {
    "model": "ride.ride",
    "pk": 27,
    "fields": {
      "status": "assigned",
      "id_rider": 8,
      "id_driver": 5,
      "pickup_latitude": 37.710719,
      "pickup_longitude": -122.339856,
      "dropoff_latitude": 37.664277,
      "dropoff_longitude": -122.145228,
      "pickup_time": "2025-05-09T10:53:18.162723+00:00"
    }
  },
  {
    "model": "ride.ride",
    "pk": 28,
    "fields": {
      "status": "en-route",
      "id_rider": 5,
      "id_driver": 4,
      "pickup_latitude": 37.826784,
      "pickup_longitude": -122.401159,
      "dropoff_latitude": 37.870126,
      "dropoff_longitude": -122.175055,
      "pickup_time": "2025-05-04T16:41:13.696521+00:00"
    }
  },
  {
    "model": "ride.ride",
    "pk": 29,
    "fields": {
      "status": "requested",
      "id_rider": 2,
      "id_driver": 7,
      "pickup_latitude": 37.761516,
      "pickup_longitude": -122.461844,
      "dropoff_latitude": 37.712666,
      "dropoff_longitude": -122.148082,
      "pickup_time": "2025-04-27T08:31:30.977843+00:00"
    }
  },
  {
    "model": "ride.ride",
    "pk": 30,
    "fields": {
      "status": "dropoff",
      "id_rider": 3,
      "id_driver": 1,
      "pickup_latitude": 37.708378,
      "pickup_longitude": -122.435321,
      "dropoff_latitude": 37.614121,
      "dropoff_longitude": -122.32113,
      "pickup_time": "2025-05-12T22:23:00.558916+00:00"
    }
  },
  {
    "model": "ride.ride",
    "pk": 31,
    "fields": {
      "status": "cancelled",
      "id_rider": 9,
      "id_driver": 1,
      "pickup_latitude": 37.673683,
      "pickup_longitude": -122.252568,
      "dropoff_latitude": 37.635671,
      "dropoff_longitude": -122.247723,
      "pickup_time": "2025-05-19T02:30:32.191071+00:00"
    }
  },
  {
    "model": "ride.ride",
    "pk": 32,
    "fields": {
      "status": "completed",
      "id_rider": 5,
      "id_driver": 8,
      "pickup_latitude": 37.667574,
      "pickup_longitude": -122.161849,
      "dropoff_latitude": 37.818906,
      "dropoff_longitude": -122.155004,
      "pickup_time": "2025-04-24T14:55:10.720026+00:00"
    }
  },
  {
    "model": "ride.ride",
    "pk": 33,
    "fields": {
      "status": "pickup",
      "id_rider": 8,
      "id_driver": 12,
      "pickup_latitude": 37.641468,
      "pickup_longitude": -122.29136,
      "dropoff_latitude": 37.732404,
      "dropoff_longitude": -122.23221,
      "pickup_time": "2025-04-30T12:58:58.049975+00:00"
    }
  },
  {
    "model": "ride.ride",
    "pk": 34,
    "fields": {
      "status": "failed",
      "id_rider": 13,
      "id_driver": 12,
      "pickup_latitude": 37.781569,
      "pickup_longitude": -122.206767,
      "dropoff_latitude": 37.670847,
      "dropoff_longitude": -122.251463,
      "pickup_time": "2025-05-22T14:18:43.977625+00:00"
    }
  },
  {
    "model": "ride.ride",
    "pk": 35,
    "fields": {
      "status": "completed",
      "id_rider": 2,
      "id_driver": 1,
      "pickup_latitude": 37.624675,
      "pickup_longitude": -122.214432,
      "dropoff_latitude": 37.832047,
      "dropoff_longitude": -122.426565,
      "pickup_time": "2025-04-27T18:57:30.601646+00:00"
    }
  },
  {
    "model": "ride.ride",
    "pk": 36,
    "fields": {
      "status": "pickup",
      "id_rider": 1,
      "id_driver": 9,
      "pickup_latitude": 37.857555,
      "pickup_longitude": -122.280053,
      "dropoff_latitude": 37.798201,
      "dropoff_longitude": -122.231281,
      "pickup_time": "2025-05-19T06:40:13.684606+00:00"
    }
  },
  {
    "model": "ride.ride",
    "pk": 37,
    "fields": {
      "status": "pickup",
      "id_rider": 13,
      "id_driver": 2,
      "pickup_latitude": 37.679224,
      "pickup_longitude": -122.225808,
      "dropoff_latitude": 37.70033,
      "dropoff_longitude": -122.165631,
      "pickup_time": "2025-05-09T02:27:05.034714+00:00"
    }
  },
  {
    "model": "ride.ride",
    "pk": 38,
    "fields": {
      "status": "failed",
      "id_rider": 7,
      "id_driver": 10,
      "pickup_latitude": 37.844784,
      "pickup_longitude": -122.15423,
      "dropoff_latitude": 37.855045,
      "dropoff_longitude": -122.353175,
      "pickup_time": "2025-05-09T17:45:30.571516+00:00"
    }
  },
  {
    "model": "ride.ride",
    "pk": 39,
    "fields": {
      "status": "failed",
      "id_rider": 9,
      "id_driver": 12,
      "pickup_latitude": 37.743624,
      "pickup_longitude": -122.288412,
      "dropoff_latitude": 37.859837,
      "dropoff_longitude": -122.313065,
      "pickup_time": "2025-05-13T19:18:28.910899+00:00"
    }
  },
  {
    "model": "ride.ride",
    "pk": 40,
    "fields": {
      "status": "dropoff",
      "id_rider": 5,
      "id_driver": 9,
      "pickup_latitude": 37.855602,
      "pickup_longitude": -122.386508,
      "dropoff_latitude": 37.675327,
      "dropoff_longitude": -122.362748,
      "pickup_time": "2025-05-10T21:46:44.118332+00:00"
    }
  },
  {
    "model": "ride.ride",
    "pk": 41,
    "fields": {
      "status": "dropoff",
      "id_rider": 7,
      "id_driver": 10,
      "pickup_latitude": 37.692252,
      "pickup_longitude": -122.300836,
      "dropoff_latitude": 37.619162,
      "dropoff_longitude": -122.230297,
      "pickup_time": "2025-04-26T13:28:10.385337+00:00"
    }
  },
  {
    "model": "ride.ride",
    "pk": 42,
    "fields": {
      "status": "en-route",
      "id_rider": 4,
      "id_driver": 9,
      "pickup_latitude": 37.664655,
      "pickup_longitude": -122.4861,
      "dropoff_latitude": 37.78799,
      "dropoff_longitude": -122.42365,
      "pickup_time": "2025-04-30T16:16:54.260077+00:00"
    }
  },
  {
    "model": "ride.ride",
    "pk": 43,
    "fields": {
      "status": "dropoff",
      "id_rider": 7,
      "id_driver": 6,
      "pickup_latitude": 37.704051,
      "pickup_longitude": -122.34463,
      "dropoff_latitude": 37.764826,
      "dropoff_longitude": -122.13281,
      "pickup_time": "2025-05-21T15:06:20.485134+00:00"
    }
  },
  {
    "model": "ride.ride",
    "pk": 44,
    "fields": {
      "status": "requested",
      "id_rider": 13,
      "id_driver": 8,
      "pickup_latitude": 37.807408,
      "pickup_longitude": -122.498432,
      "dropoff_latitude": 37.684043,
      "dropoff_longitude": -122.234933,
      "pickup_time": "2025-05-03T16:18:28.162361+00:00"
    }
  },
  {
    "model": "ride.ride",
    "pk": 45,
    "fields": {
      "status": "cancelled",
      "id_rider": 1,
      "id_driver": 10,
      "pickup_latitude": 37.805274,
      "pickup_longitude": -122.230545,
      "dropoff_latitude": 37.796175,
      "dropoff_longitude": -122.499867,
      "pickup_time": "2025-05-19T17:15:09.373952+00:00"
    }
  },
  {
    "model": "ride.ride",
    "pk": 46,
    "fields": {
      "status": "completed",
      "id_rider": 7,
      "id_driver": 9,
      "pickup_latitude": 37.73165,
      "pickup_longitude": -122.413006,
      "dropoff_latitude": 37.661446,
      "dropoff_longitude": -122.486124,
      "pickup_time": "2025-05-06T01:36:31.963778+00:00"
    }
  },
  {
    "model": "ride.ride",
    "pk": 47,
    "fields": {
      "status": "cancelled",
      "id_rider": 10,
      "id_driver": 7,
      "pickup_latitude": 37.807475,
      "pickup_longitude": -122.169427,
      "dropoff_latitude": 37.839995,
      "dropoff_longitude": -122.204959,
      "pickup_time": "2025-05-14T08:57:59.280201+00:00"
    }
  },
  {
    "model": "ride.ride",
    "pk": 48,
    "fields": {
      "status": "requested",
      "id_rider": 5,
      "id_driver": 4,
      "pickup_latitude": 37.891251,
      "pickup_longitude": -122.435634,
      "dropoff_latitude": 37.896728,
      "dropoff_longitude": -122.417457,
      "pickup_time": "2025-05-13T05:55:06.800339+00:00"
    }
  },
  {
    "model": "ride.ride",
    "pk": 49,
    "fields": {
      "status": "pickup",
      "id_rider": 12,
      "id_driver": 5,
      "pickup_latitude": 37.663261,
      "pickup_longitude": -122.431009,
      "dropoff_latitude": 37.86439,
      "dropoff_longitude": -122.26866,
      "pickup_time": "2025-05-10T23:52:05.022267+00:00"
    }
  },
  {
    "model": "ride.ride",
    "pk": 50,
    "fields": {
      "status": "failed",
      "id_rider": 8,
      "id_driver": 3,
      "pickup_latitude": 37.855379,
      "pickup_longitude": -122.471618,
      "dropoff_latitude": 37.831254,
      "dropoff_longitude": -122.459225,
      "pickup_time": "2025-05-17T04:43:41.653412+00:00"
    }
  }
]